odoo/addons/pos_receipt_xml_header_footer/README.rst
odoo/addons/pos_receipt_xml_header_footer/__init__.py
odoo/addons/pos_receipt_xml_header_footer/__manifest__.py
odoo/addons/pos_receipt_xml_header_footer/i18n/pos_receipt_xml_header_footer.pot
odoo/addons/pos_receipt_xml_header_footer/readme/CONTRIBUTORS.rst
odoo/addons/pos_receipt_xml_header_footer/readme/DESCRIPTION.rst
odoo/addons/pos_receipt_xml_header_footer/readme/USAGE.rst
odoo/addons/pos_receipt_xml_header_footer/static/description/icon.png
odoo/addons/pos_receipt_xml_header_footer/static/description/index.html
odoo/addons/pos_receipt_xml_header_footer/static/src/xml/pos.xml
odoo12_addon_pos_receipt_xml_header_footer-12.0.1.0.1.dist-info/METADATA
odoo12_addon_pos_receipt_xml_header_footer-12.0.1.0.1.dist-info/WHEEL
odoo12_addon_pos_receipt_xml_header_footer-12.0.1.0.1.dist-info/top_level.txt
odoo12_addon_pos_receipt_xml_header_footer-12.0.1.0.1.dist-info/RECORD
