Metadata-Version: 2.1
Name: odoo12-addon-pos-receipt-xml-header-footer
Version: 12.0.1.0.1
Summary: Add the ability to use XML/HTML in the header and footer of a receipt
Home-page: https://github.com/OCA/pos
Author: Coop IT Easy SCRLfs, Odoo Community Association (OCA)
Author-email: support@odoo-community.org
License: AGPL-3
Platform: UNKNOWN
Classifier: Programming Language :: Python
Classifier: Framework :: Odoo
Classifier: Framework :: Odoo :: 12.0
Classifier: License :: OSI Approved :: GNU Affero General Public License v3
Requires-Python: >=3.5
Requires-Dist: odoo (<12.1dev,>=12.0a)
